sword2/__init__.py
sword2/atom_objects.py
sword2/auto_discovery.py
sword2/collection.py
sword2/connection.py
sword2/deposit_receipt.py
sword2/error_document.py
sword2/exceptions.py
sword2/http_layer.py
sword2/implementation_info.py
sword2/server_errors.py
sword2/service_document.py
sword2/statement.py
sword2/sword2_logging.py
sword2/transaction_history.py
sword2/utils.py
sword2-0.3.dist-info/LICENSE.txt
sword2-0.3.dist-info/WHEEL
sword2-0.3.dist-info/METADATA
sword2-0.3.dist-info/RECORD
