Metadata-Version: 2.1
Name: sword2
Version: 0.3
Summary: SWORDv2 Python client
Home-page: http://swordapp.org/
License: Apache-2.0
Keywords: sword-app,atom,sword2,http
Author: Ben O'Steen
Author-email: beno@gmail.com
Maintainer: Cottage Labs
Maintainer-email: us@cottagelabs.com
Requires-Python: >=3.7
Classifier: Development Status :: 5 - Production/Stable
Classifier: Environment :: Console
Classifier: Environment :: Web Environment
Classifier: Intended Audience :: Developers
Classifier: Intended Audience :: Information Technology
Classifier: Intended Audience :: Science/Research
Classifier: License :: OSI Approved :: Apache Software License
Classifier: Natural Language :: English
Classifier: Operating System :: OS Independent
Classifier: Programming Language :: Python :: 3
Classifier: Programming Language :: Python :: 3.7
Classifier: Programming Language :: Python :: 3.8
Classifier: Programming Language :: Python :: 3.9
Classifier: Topic :: Communications
Classifier: Topic :: Internet
Classifier: Topic :: Internet :: WWW/HTTP
Classifier: Topic :: Software Development :: Libraries :: Python Modules
Requires-Dist: httplib2 (>=0.18.1,<0.19.0)
Requires-Dist: lxml (>=4.6.2,<5.0.0)
Project-URL: Documentation, https://github.com/swordapp/python-client-sword2/wiki
Project-URL: Repository, https://github.com/swordapp/python-client-sword2
